crypto_fate-0.3.0.dist-info/METADATA
crypto_fate-0.3.0.dist-info/WHEEL
fate_crypto/hash/__init__.pyi
fate_crypto/hash/__init__.py
fate_crypto/__init__.py
fate_crypto/psi/__init__.pyi
fate_crypto/psi/__init__.py
fate_crypto/fate_crypto.cpython-310-darwin.so
crypto_fate-0.3.0.dist-info/RECORD
